DECODER3TO8/src/decoder3_to_8.v
// Decoder 2-to-4 module
module decoder2_to_4(in, en, out);
  input [1:0] in;
  input en;
  output [3:0] out;
  reg [3:0] out;
  
  always @(in or en) begin
    if (en) begin
      out = 4'd0;
      case (in)
        2'b00: out[0] = 1'b1;
        2'b01: out[1] = 1'b1;
        2'b10: out[2] = 1'b1;
        2'b11: out[3] = 1'b1;
        default: out = 4'd0;
      endcase
    end
    else
      out = 4'd0;
  end
endmodule

// Decoder 3-to-8 using two 2-to-4 decoders
module decoder3_to_8(in, out, en);
  input [2:0] in;
  input en;
  output [7:0] out;
  wire [3:0] out_low, out_high;
  wire en_low, en_high;
  
  // Bit cao nhất (in[2]) quyết định decoder nào được kích hoạt
  // Khi in[2]=0: kích hoạt decoder thấp (out[3:0])
  // Khi in[2]=1: kích hoạt decoder cao (out[7:4])
  assign en_low = en & ~in[2];   // Enable decoder thấp khi in[2]=0
  assign en_high = en & in[2];    // Enable decoder cao khi in[2]=1
  
  // Decoder thấp: xử lý out[3:0] với input in[1:0]
  decoder2_to_4 dec_low(
    .in(in[1:0]),
    .en(en_low),
    .out(out_low)
  );
  
  // Decoder cao: xử lý out[7:4] với input in[1:0]
  decoder2_to_4 dec_high(
    .in(in[1:0]),
    .en(en_high),
    .out(out_high)
  );
  
  // Kết nối output
  assign out = {out_high, out_low};
  
endmodule

DECODER3TO8/verify/decoder_tb.v
module decoder_tb;
wire [7:0] out;
reg en;
reg [2:0] in;
integer i;

decoder3_to_8 dut(in,out,en);

initial begin  
 // Tạo file .vcd để xem waveform bằng GTKWave
 $dumpfile("decoder_waveform.vcd");
 $dumpvars(0, decoder_tb);
 
 $monitor( "en=%b, in=%d, out=%b ", en, in, out);
   for ( i=0; i<16; i=i+1) 
        begin
           {en,in}  = i;
            #10; // Tăng delay để dễ xem waveform
        end
 $finish;
end
endmodule

DECODER3TO8/verify/decoder_waveform.vcd
$date
	Mon Nov 10 17:36:10 2025
$end
$version
	Icarus Verilog
$end
$timescale
	1s
$end
$scope module decoder_tb $end
$var wire 8 ! out [7:0] $end
$var reg 1 " en $end
$var reg 3 # in [2:0] $end
$var integer 32 $ i [31:0] $end
$scope module dut $end
$var wire 1 " en $end
$var wire 3 % in [2:0] $end
$var reg 8 & out [7:0] $end
$upscope $end
$upscope $end
$enddefinitions $end
$comment Show the parameter values. $end
$dumpall
$end
#0
$dumpvars
b0 &
b0 %
b0 $
b0 #
0"
b0 !
$end
#10
b1 #
b1 %
b1 $
#20
b10 #
b10 %
b10 $
#30
b11 #
b11 %
b11 $
#40
b100 #
b100 %
b100 $
#50
b101 #
b101 %
b101 $
#60
b110 #
b110 %
b110 $
#70
b111 #
b111 %
b111 $
#80
b1 !
b1 &
1"
b0 #
b0 %
b1000 $
#90
b10 !
b10 &
b1 #
b1 %
b1001 $
#100
b100 !
b100 &
b10 #
b10 %
b1010 $
#110
b1000 !
b1000 &
b11 #
b11 %
b1011 $
#120
b10000 !
b10000 &
b100 #
b100 %
b1100 $
#130
b100000 !
b100000 &
b101 #
b101 %
b1101 $
#140
b1000000 !
b1000000 &
b110 #
b110 %
b1110 $
#150
b10000000 !
b10000000 &
b111 #
b111 %
b1111 $
#160
b10000 $
